df_db_connector/__init__.py
df_db_connector/db_connector.py
df_db_connector/json_connector.py
df_db_connector/mongo_connector.py
df_db_connector/pickle_connector.py
df_db_connector/protocol.py
df_db_connector/protocols.json
df_db_connector/redis_connector.py
df_db_connector/shelve_connector.py
df_db_connector/sql_connector.py
df_db_connector/ydb_connector.py
examples/__init__.py
examples/basic.py
examples/db.py
examples/flask.py
examples/utils.py
examples/ydb.py
tests/__init__.py
tests/conftest.py
tests/test_dbs.py
df_db_connector-0.3.1.dist-info/LICENSE
df_db_connector-0.3.1.dist-info/METADATA
df_db_connector-0.3.1.dist-info/WHEEL
df_db_connector-0.3.1.dist-info/top_level.txt
df_db_connector-0.3.1.dist-info/RECORD
