Metadata-Version: 2.1
Name: df-db-connector
Version: 0.3.1
Summary: [There](https://github.com/deepmipt/dialog_flow_db_connector) is an addon for the [Dialog Flow Framework](https://github.com/deepmipt/dialog_flow_engine), a minimalistic open-source engine for conversational services.
Home-page: https://github.com/deepmipt/dialog_flow_db_connector
Author: Denis Kuznetsov, Daniil Ignatiev
Author-email: kuznetsov.den.p@gmail.com
Keywords: chatbots,df-db-connector
Classifier: Development Status :: 2 - Pre-Alpha
Classifier: Intended Audience :: Developers
Classifier: Topic :: Software Development :: Build Tools
Classifier: License :: OSI Approved :: Apache Software License
Classifier: Operating System :: OS Independent
Classifier: Programming Language :: Python :: 3
Classifier: Programming Language :: Python :: 3.6
Classifier: Programming Language :: Python :: 3.7
Classifier: Programming Language :: Python :: 3.8
Classifier: Programming Language :: Python :: 3.9
Classifier: Programming Language :: Python :: 3 :: Only
Requires-Python: >=3.5, <4
License-File: LICENSE
Requires-Dist: df-engine (>=0.9.0)
Provides-Extra: mongodb
Requires-Dist: pymongo (>=4.0.2) ; extra == 'mongodb'
Requires-Dist: bson (>=0.5.10) ; extra == 'mongodb'
Provides-Extra: mysql
Requires-Dist: sqlalchemy (>=1.4.27) ; extra == 'mysql'
Requires-Dist: pymysql (>=1.0.2) ; extra == 'mysql'
Requires-Dist: cryptography-36.0.2 ; extra == 'mysql'
Provides-Extra: postgresql
Requires-Dist: sqlalchemy (>=1.4.27) ; extra == 'postgresql'
Requires-Dist: psycopg2-binary (>=2.9.2) ; extra == 'postgresql'
Provides-Extra: redis
Requires-Dist: redis (>=4.1.2) ; extra == 'redis'
Provides-Extra: sqlite
Requires-Dist: sqlalchemy (>=1.4.27) ; extra == 'sqlite'
Provides-Extra: ydb
Requires-Dist: ydb (>=2.5.0) ; extra == 'ydb'
